{
  "Full Oscillatory BifurcationGAN": {
    "metrics": {
      "FID": 5.4757640147057,
      "FID_std": 0.5962394085997511,
      "FID_min": 4.634652653352477,
      "FID_max": 5.9478066539540455,
      "MMD": 0.7321350574493408,
      "MMD_std": 0.13569147884845734,
      "MMD_min": 0.5967528223991394,
      "MMD_max": 0.9176056385040283,
      "Wasserstein": 1.0634312629699707,
      "Wasserstein_std": 0.10566174238920212,
      "Wasserstein_min": 0.9218810796737671,
      "Wasserstein_max": 1.1756703853607178,
      "JS_Divergence": 0.5835513585398848,
      "JS_Divergence_std": 0.03259582708734102,
      "JS_Divergence_min": 0.5412212456357995,
      "JS_Divergence_max": 0.6205231563198323,
      "KS_Statistic": 0.6910833333333333,
      "KS_Statistic_std": 0.06950722717552203,
      "KS_Statistic_min": 0.5955833333333334,
      "KS_Statistic_max": 0.759,
      "ACF_Similarity": 0.4705106647024098,
      "ACF_Similarity_std": 0.07694116844751496,
      "ACF_Similarity_min": 0.36628552032132367,
      "ACF_Similarity_max": 0.5496926765280767,
      "PSD_Similarity": 0.9872260797147888,
      "PSD_Similarity_std": 0.0050074161936655166,
      "PSD_Similarity_min": 0.9833593277453879,
      "PSD_Similarity_max": 0.9942973051825149,
      "Composite_Score": 0.35281296189097494,
      "Composite_Score_std": 0.03135261347814469,
      "Composite_Score_min": 0.32097374519753785,
      "Composite_Score_max": 0.39545667486490554
    },
    "config": {
      "name": "Full Oscillatory BifurcationGAN",
      "use_bifurcation": true,
      "use_oscillators": true,
      "use_coupling": true,
      "use_multiscale": true,
      "use_noise": true,
      "description": "Complete model with all components"
    },
    "composite_score": 0.35281296189097494,
    "composite_std": 0.03135261347814469
  },
  "No Bifurcation": {
    "metrics": {
      "FID": 2.6290814006746794,
      "FID_std": 1.6530717552943341,
      "FID_min": 0.4933755382456885,
      "FID_max": 4.52036598911257,
      "MMD": 0.3808921277523041,
      "MMD_std": 0.2364347279071808,
      "MMD_min": 0.06261265277862549,
      "MMD_max": 0.628777027130127,
      "Wasserstein": 0.7695040702819824,
      "Wasserstein_std": 0.32842347025871277,
      "Wasserstein_min": 0.3258715271949768,
      "Wasserstein_max": 1.1104236841201782,
      "JS_Divergence": 0.41485465117404297,
      "JS_Divergence_std": 0.16254332798923346,
      "JS_Divergence_min": 0.1978313611655477,
      "JS_Divergence_max": 0.5889877020314092,
      "KS_Statistic": 0.5325277777777777,
      "KS_Statistic_std": 0.2144081575516458,
      "KS_Statistic_min": 0.24341666666666661,
      "KS_Statistic_max": 0.75625,
      "ACF_Similarity": 0.38816398540815816,
      "ACF_Similarity_std": 0.06206764566643803,
      "ACF_Similarity_min": 0.33379246913517646,
      "ACF_Similarity_max": 0.47502714815891167,
      "PSD_Similarity": 0.9929690592442082,
      "PSD_Similarity_std": 0.002445488269016211,
      "PSD_Similarity_min": 0.9896332528997005,
      "PSD_Similarity_max": 0.9954274789152151,
      "Composite_Score": 0.47108386819952375,
      "Composite_Score_std": 0.1447225890190943,
      "Composite_Score_min": 0.32927916740012697,
      "Composite_Score_max": 0.6697966711529146
    },
    "config": {
      "name": "No Bifurcation",
      "use_bifurcation": false,
      "use_oscillators": true,
      "use_coupling": true,
      "use_multiscale": true,
      "use_noise": true,
      "description": "Remove bifurcation dynamics"
    },
    "composite_score": 0.47108386819952375,
    "composite_std": 0.1447225890190943
  },
  "No Oscillators": {
    "metrics": {
      "FID": 1.9250442999750124,
      "FID_std": 1.923109314056009,
      "FID_min": 0.41024000344826494,
      "FID_max": 4.638603422545801,
      "MMD": 0.2830071747303009,
      "MMD_std": 0.1899150311946869,
      "MMD_min": 0.1361895203590393,
      "MMD_max": 0.551185131072998,
      "Wasserstein": 0.6394596695899963,
      "Wasserstein_std": 0.3878936767578125,
      "Wasserstein_min": 0.2725425660610199,
      "Wasserstein_max": 1.1760770082473755,
      "JS_Divergence": 0.3413358522700618,
      "JS_Divergence_std": 0.1975748936079758,
      "JS_Divergence_min": 0.19201621343816472,
      "JS_Divergence_max": 0.6205231563198323,
      "KS_Statistic": 0.4261388888888889,
      "KS_Statistic_std": 0.23665528467674685,
      "KS_Statistic_min": 0.24341666666666661,
      "KS_Statistic_max": 0.7603333333333333,
      "ACF_Similarity": 0.373635176581526,
      "ACF_Similarity_std": 0.13753928396092135,
      "ACF_Similarity_min": 0.19247364582129667,
      "ACF_Similarity_max": 0.52554258199827,
      "PSD_Similarity": 0.9940128259669829,
      "PSD_Similarity_std": 0.0011676700504460202,
      "PSD_Similarity_min": 0.9926979374503445,
      "PSD_Similarity_max": 0.9955354182829618,
      "Composite_Score": 0.5474747490442564,
      "Composite_Score_std": 0.1728417924087986,
      "Composite_Score_min": 0.30334445554310063,
      "Composite_Score_max": 0.6801100259221791
    },
    "config": {
      "name": "No Oscillators",
      "use_bifurcation": true,
      "use_oscillators": false,
      "use_coupling": false,
      "use_multiscale": true,
      "use_noise": true,
      "description": "Remove coupled oscillators"
    },
    "composite_score": 0.5474747490442564,
    "composite_std": 0.1728417924087986
  },
  "No Coupling": {
    "metrics": {
      "FID": 4.497960056892831,
      "FID_std": 0.955522282879012,
      "FID_min": 3.3174837089925258,
      "FID_max": 5.657751515139937,
      "MMD": 0.6079201102256775,
      "MMD_std": 0.17750553786754608,
      "MMD_min": 0.454634428024292,
      "MMD_max": 0.8567255139350891,
      "Wasserstein": 0.953218400478363,
      "Wasserstein_std": 0.13590140640735626,
      "Wasserstein_min": 0.7787321209907532,
      "Wasserstein_max": 1.1102447509765625,
      "JS_Divergence": 0.5572954924841874,
      "JS_Divergence_std": 0.03867645379608706,
      "JS_Divergence_min": 0.5028423286685758,
      "JS_Divergence_max": 0.5889877020314092,
      "KS_Statistic": 0.63675,
      "KS_Statistic_std": 0.08877909017247164,
      "KS_Statistic_min": 0.5410833333333334,
      "KS_Statistic_max": 0.755,
      "ACF_Similarity": 0.48802114075336983,
      "ACF_Similarity_std": 0.047640849994665925,
      "ACF_Similarity_min": 0.42130655695159314,
      "ACF_Similarity_max": 0.5295239291669442,
      "PSD_Similarity": 0.9938924204988956,
      "PSD_Similarity_std": 0.002678339987945034,
      "PSD_Similarity_min": 0.990115185967098,
      "PSD_Similarity_max": 0.996025234622647,
      "Composite_Score": 0.3746891218926935,
      "Composite_Score_std": 0.026901853391547263,
      "Composite_Score_min": 0.3382667839944822,
      "Composite_Score_max": 0.4024199836084721
    },
    "config": {
      "name": "No Coupling",
      "use_bifurcation": true,
      "use_oscillators": true,
      "use_coupling": false,
      "use_multiscale": true,
      "use_noise": true,
      "description": "Remove oscillator coupling"
    },
    "composite_score": 0.3746891218926935,
    "composite_std": 0.026901853391547263
  },
  "No Multiscale": {
    "metrics": {
      "FID": 4.289602861083671,
      "FID_std": 0.4130661421057967,
      "FID_min": 3.709423712119557,
      "FID_max": 4.638680340781171,
      "MMD": 0.5374372005462646,
      "MMD_std": 0.10839959233999252,
      "MMD_min": 0.44128090143203735,
      "MMD_max": 0.6889135241508484,
      "Wasserstein": 1.0984781980514526,
      "Wasserstein_std": 0.06877243518829346,
      "Wasserstein_min": 1.0089025497436523,
      "Wasserstein_max": 1.176077961921692,
      "JS_Divergence": 0.5482441881470802,
      "JS_Divergence_std": 0.08094929403460631,
      "JS_Divergence_min": 0.4352217060899991,
      "JS_Divergence_max": 0.6205231563198323,
      "KS_Statistic": 0.7000277777777777,
      "KS_Statistic_std": 0.08264746454103558,
      "KS_Statistic_min": 0.5831666666666666,
      "KS_Statistic_max": 0.7603333333333333,
      "ACF_Similarity": 0.5107872138480348,
      "ACF_Similarity_std": 0.13820736001185913,
      "ACF_Similarity_min": 0.31679049723458863,
      "ACF_Similarity_max": 0.6284221173979221,
      "PSD_Similarity": 0.9972387647149558,
      "PSD_Similarity_std": 0.0008245289142905024,
      "PSD_Similarity_min": 0.9964185842631762,
      "PSD_Similarity_max": 0.9983666640489242,
      "Composite_Score": 0.42645718920820924,
      "Composite_Score_std": 0.12988894150348224,
      "Composite_Score_min": 0.315866613869775,
      "Composite_Score_max": 0.6087721571324094
    },
    "config": {
      "name": "No Multiscale",
      "use_bifurcation": true,
      "use_oscillators": true,
      "use_coupling": true,
      "use_multiscale": false,
      "use_noise": true,
      "description": "Remove multiscale processing"
    },
    "composite_score": 0.42645718920820924,
    "composite_std": 0.12988894150348224
  },
  "No Noise": {
    "metrics": {
      "FID": 5.027381089221103,
      "FID_std": 0.6364776989093196,
      "FID_min": 4.518519046189111,
      "FID_max": 5.924813166478327,
      "MMD": 0.6266666054725647,
      "MMD_std": 0.12416478246450424,
      "MMD_min": 0.4572715759277344,
      "MMD_max": 0.7514182329177856,
      "Wasserstein": 1.126109004020691,
      "Wasserstein_std": 0.03612653911113739,
      "Wasserstein_min": 1.0919723510742188,
      "Wasserstein_max": 1.17609703540802,
      "JS_Divergence": 0.5994735106717547,
      "JS_Divergence_std": 0.014884381266700454,
      "JS_Divergence_min": 0.5889096736640226,
      "JS_Divergence_max": 0.6205231563198323,
      "KS_Statistic": 0.7432777777777778,
      "KS_Statistic_std": 0.02019125375986004,
      "KS_Statistic_min": 0.7149166666666666,
      "KS_Statistic_max": 0.7603333333333333,
      "ACF_Similarity": 0.5101765731741273,
      "ACF_Similarity_std": 0.11626125662056333,
      "ACF_Similarity_min": 0.3521204309394611,
      "ACF_Similarity_max": 0.628431059025794,
      "PSD_Similarity": 0.9954680404984497,
      "PSD_Similarity_std": 0.0012729011583378922,
      "PSD_Similarity_min": 0.9940960408422047,
      "PSD_Similarity_max": 0.9971633117201005,
      "Composite_Score": 0.3426396924932664,
      "Composite_Score_std": 0.008125218619159724,
      "Composite_Score_min": 0.3312861003791663,
      "Composite_Score_max": 0.3498496962967397
    },
    "config": {
      "name": "No Noise",
      "use_bifurcation": true,
      "use_oscillators": true,
      "use_coupling": true,
      "use_multiscale": true,
      "use_noise": false,
      "description": "Remove phase noise"
    },
    "composite_score": 0.3426396924932664,
    "composite_std": 0.008125218619159724
  },
  "Vanilla GAN Baseline": {
    "metrics": {
      "FID": 1.5839607694246078,
      "FID_std": 1.0718015270512349,
      "FID_min": 0.3713873674092174,
      "FID_max": 2.9778940146560777,
      "MMD": 0.2136264592409134,
      "MMD_std": 0.14712417125701904,
      "MMD_min": 0.05366009473800659,
      "MMD_max": 0.40883272886276245,
      "Wasserstein": 0.5475104451179504,
      "Wasserstein_std": 0.1689266711473465,
      "Wasserstein_min": 0.38199010491371155,
      "Wasserstein_max": 0.7794570326805115,
      "JS_Divergence": 0.3654968974129606,
      "JS_Divergence_std": 0.03439480775116117,
      "JS_Divergence_min": 0.31685980695910887,
      "JS_Divergence_max": 0.39038926708768346,
      "KS_Statistic": 0.3429722222222222,
      "KS_Statistic_std": 0.08424010364267363,
      "KS_Statistic_min": 0.24341666666666661,
      "KS_Statistic_max": 0.44941666666666663,
      "ACF_Similarity": 0.5123408459695686,
      "ACF_Similarity_std": 0.1045413266667422,
      "ACF_Similarity_min": 0.3697904552453031,
      "ACF_Similarity_max": 0.6175700256359502,
      "PSD_Similarity": 0.9933519658211488,
      "PSD_Similarity_std": 0.0021745171077112257,
      "PSD_Similarity_min": 0.9902768541953635,
      "PSD_Similarity_max": 0.9949130449057764,
      "Composite_Score": 0.6153062249741831,
      "Composite_Score_std": 0.01705754557674787,
      "Composite_Score_min": 0.5935346688691405,
      "Composite_Score_max": 0.6351886301851446
    },
    "config": {
      "name": "Vanilla GAN Baseline",
      "use_bifurcation": false,
      "use_oscillators": false,
      "use_coupling": false,
      "use_multiscale": false,
      "use_noise": false,
      "description": "Basic GAN without any enhancements"
    },
    "composite_score": 0.6153062249741831,
    "composite_std": 0.01705754557674787
  }
}